cosmian_anonymization/__init__.py
cosmian_anonymization/anonymize.py
cosmian_anonymization/conversion_helper.py
cosmian_anonymization/method_parser.py
cosmian_anonymization/noise_correlation.py
cosmian_anonymization/noise_parser.py
cosmian_anonymization-1.2.4.dist-info/LICENSE.md
cosmian_anonymization-1.2.4.dist-info/METADATA
cosmian_anonymization-1.2.4.dist-info/WHEEL
cosmian_anonymization-1.2.4.dist-info/entry_points.txt
cosmian_anonymization-1.2.4.dist-info/RECORD
