Metadata-Version: 2.1
Name: cosmian-anonymization
Version: 1.2.4
Summary: Cosmian Anonymization library in Python
Author: Hugo Rosenkranz-Costa
Author-email: hugo.rosenkranz@cosmian.com
Requires-Python: >=3.8,<4.0
Classifier: Programming Language :: Python :: 3
Classifier: Programming Language :: Python :: 3.8
Classifier: Programming Language :: Python :: 3.9
Classifier: Programming Language :: Python :: 3.10
Classifier: Programming Language :: Python :: 3.11
Requires-Dist: cloudproof-py (>=4.0,<5.0)
Requires-Dist: pandas (>=2.0,<3.0)
Requires-Dist: pyhumps (>=3.8,<4.0)
Requires-Dist: python-dateutil (>=2.8,<3.0)
